<?xml version="1.0" encoding="UTF-8"?>
<OfficeApp xmlns="http://schemas.microsoft.com/office/appforoffice/1.1"
  xmlns:xsi="http://www.w3.org/2001/XMLSchema-instance"
  xmlns:bt="http://schemas.microsoft.com/office/officeappbasictypes/1.0"
  xmlns:ovr="http://schemas.microsoft.com/office/mailappversionoverrides"
  xsi:type="MailApp">
  <Id>cbfa1f46-148d-4780-8a04-a52ce1cd8eaf</Id>
  <Version>1.0.2.0</Version>
  <ProviderName>WeCalendar</ProviderName>
  <DefaultLocale>en-US</DefaultLocale>
  <DisplayName DefaultValue="WeCalendar"/>
  <Description DefaultValue="Insert your WeCalendar booking link into an email you're composing."/>
  <IconUrl DefaultValue="https://wecalendar.github.io/wecal-64.png"/>
  <HighResolutionIconUrl DefaultValue="https://wecalendar.github.io/wecal-128.png"/>
  <SupportUrl DefaultValue="https://wecalendar.github.io/"/>
  <AppDomains>
    <AppDomain>https://wecalendar.github.io</AppDomain>
  </AppDomains>
  <Hosts>
    <Host Name="Mailbox"/>
  </Hosts>
  <Requirements>
    <Sets>
      <Set Name="Mailbox" MinVersion="1.3"/>
    </Sets>
  </Requirements>
  <FormSettings>
    <Form xsi:type="ItemRead">
      <DesktopSettings>
        <SourceLocation DefaultValue="https://wecalendar.github.io/outlook.html?v=3"/>
        <RequestedHeight>260</RequestedHeight>
      </DesktopSettings>
    </Form>
  </FormSettings>
  <Permissions>ReadWriteItem</Permissions>
  <Rule xsi:type="RuleCollection" Mode="Or">
    <Rule xsi:type="ItemIs" ItemType="Message" FormType="ReadOrEdit"/>
  </Rule>
  <DisableEntityHighlighting>false</DisableEntityHighlighting>
  <VersionOverrides xmlns="http://schemas.microsoft.com/office/mailappversionoverrides" xsi:type="VersionOverridesV1_0">
    <Requirements>
      <bt:Sets DefaultMinVersion="1.3">
        <bt:Set Name="Mailbox"/>
      </bt:Sets>
    </Requirements>
    <Hosts>
      <Host xsi:type="MailHost">
        <DesktopFormFactor>
          <ExtensionPoint xsi:type="MessageComposeCommandSurface">
            <OfficeTab id="TabDefault">
              <Group id="weCalGroup">
                <Label resid="grpLabel"/>
                <Control xsi:type="Button" id="weCalOpenBtn">
                  <Label resid="btnLabel"/>
                  <Supertip>
                    <Title resid="btnLabel"/>
                    <Description resid="btnTip"/>
                  </Supertip>
                  <Icon>
                    <bt:Image size="16" resid="icon16"/>
                    <bt:Image size="32" resid="icon32"/>
                    <bt:Image size="80" resid="icon80"/>
                  </Icon>
                  <Action xsi:type="ShowTaskpane">
                    <SourceLocation resid="taskpaneUrl"/>
                  </Action>
                </Control>
              </Group>
            </OfficeTab>
          </ExtensionPoint>
        </DesktopFormFactor>
      </Host>
    </Hosts>
    <Resources>
      <bt:Images>
        <bt:Image id="icon16" DefaultValue="https://wecalendar.github.io/wecal-16.png"/>
        <bt:Image id="icon32" DefaultValue="https://wecalendar.github.io/wecal-32.png"/>
        <bt:Image id="icon80" DefaultValue="https://wecalendar.github.io/wecal-80.png"/>
      </bt:Images>
      <bt:Urls>
        <bt:Url id="taskpaneUrl" DefaultValue="https://wecalendar.github.io/outlook.html?v=3"/>
      </bt:Urls>
      <bt:ShortStrings>
        <bt:String id="grpLabel" DefaultValue="WeCalendar"/>
        <bt:String id="btnLabel" DefaultValue="WeCalendar"/>
      </bt:ShortStrings>
      <bt:LongStrings>
        <bt:String id="btnTip" DefaultValue="Insert your WeCalendar booking link into this email."/>
      </bt:LongStrings>
    </Resources>
  </VersionOverrides>
</OfficeApp>
